casbin_redis_watcher/__init__.py
casbin_redis_watcher/watcher.py
pycasbin_redis_watcher-0.1.0.dist-info/LICENSE.txt
pycasbin_redis_watcher-0.1.0.dist-info/METADATA
pycasbin_redis_watcher-0.1.0.dist-info/WHEEL
pycasbin_redis_watcher-0.1.0.dist-info/top_level.txt
pycasbin_redis_watcher-0.1.0.dist-info/RECORD
