Metadata-Version: 2.1
Name: pycasbin-redis-watcher
Version: 0.1.0
Summary: Redis watcher adapter for pycasbin
Home-page: https://github.com/sciencelogic/pycasbin-redis-watcher
Author: ScienceLogic
License: MIT
Download-URL: https://github.com/sciencelogic/pycasbin-redis-watcher/tarball/0.1.0
Keywords: pycasbin,casbin,flask,rbac
Platform: UNKNOWN
Classifier: Development Status :: 3 - Alpha
Classifier: Intended Audience :: Developers
Classifier: Programming Language :: Python :: 3
Requires-Python: >3.5
Requires-Dist: redis
Requires-Dist: casbin
